purplecaffeine/__init__.py
purplecaffeine/core.py
purplecaffeine/exception.py
purplecaffeine/widget.py
purplecaffeine/helpers/__init__.py
purplecaffeine/helpers/conf.py
purplecaffeine/utils/__init__.py
purplecaffeine/utils/json.py
tests/__init__.py
tests/test_storage.py
tests/test_trial.py
tests/test_widget.py
tests/helpers/__init__.py
tests/helpers/test_conf.py
tests/utils/__init__.py
tests/utils/test_json.py
purplecaffeine-0.2.5.dist-info/METADATA
purplecaffeine-0.2.5.dist-info/WHEEL
purplecaffeine-0.2.5.dist-info/top_level.txt
purplecaffeine-0.2.5.dist-info/RECORD
