Metadata-Version: 2.1
Name: purplecaffeine
Version: 0.2.5
Summary: PurpleCaffeine: tracking of quantum programs and experiments
Home-page: UNKNOWN
License: UNKNOWN
Keywords: quantum tracking experiments
Platform: UNKNOWN
Classifier: Intended Audience :: Developers
Classifier: Intended Audience :: Science/Research
Classifier: License :: OSI Approved :: Apache Software License
Classifier: Natural Language :: English
Classifier: Operating System :: MacOS
Classifier: Operating System :: POSIX :: Linux
Classifier: Operating System :: Microsoft :: Windows
Classifier: Programming Language :: Python :: 3.7
Classifier: Programming Language :: Python :: 3.8
Classifier: Programming Language :: Python :: 3.9
Classifier: Programming Language :: Python :: 3.10
Classifier: Topic :: Scientific/Engineering :: Physics
Requires-Python: >=3.7
Requires-Dist: qiskit >=0.43.0
Requires-Dist: qiskit-ibm-runtime >=0.10.0
Requires-Dist: pympler ~=1.0
Requires-Dist: boto3 >=1.26.133
Requires-Dist: ipywidgets >=8.0.7
Requires-Dist: matplotlib >=3.7.1
Requires-Dist: pandas >=2.0.2
Requires-Dist: pylatexenc >=2.10
